{
	"DataValidate": {
		"username": "standard_user",
		"password": "secret_sauce"
	},

	"usernameBlocked": "locked_out_user",

	"UserNotExist": "Lucas",

	"passwordInvalid": "passwordNotExist",

	"userWithoutData": "",

	"passwordWithoutData": "",

	"MsgsError": {
		"blocked": "Epic sadface: Sorry, this user has been locked out.",
		"invalid": "Epic sadface: Username and password do not match any user in this service",
		"usernameError": "Epic sadface: Username is required",
		"passwordError": "Epic sadface: Password is required"
	}
}
